tiny_data_warehouse/__init__.py
tiny_data_warehouse/base_table.py
tiny_data_warehouse/data_warehouse.py
tiny_data_warehouse-0.3.2.dist-info/METADATA
tiny_data_warehouse-0.3.2.dist-info/WHEEL
tiny_data_warehouse-0.3.2.dist-info/entry_points.txt
tiny_data_warehouse-0.3.2.dist-info/licenses/LICENSE.md
tiny_data_warehouse-0.3.2.dist-info/RECORD
