Metadata-Version: 2.4
Name: tiny-data-warehouse
Version: 0.3.2
Summary: 
License-File: LICENSE.md
Author: Jean Carlo Machado
Author-email: jean.machado@getyourguide.com
Requires-Python: >=3.12,<4.0
Classifier: Programming Language :: Python :: 3
Classifier: Programming Language :: Python :: 3.12
Classifier: Programming Language :: Python :: 3.13
Classifier: Programming Language :: Python :: 3.14
Requires-Dist: filelock
Requires-Dist: fire
Requires-Dist: matplotlib
Requires-Dist: pandas
Requires-Dist: pyarrow
Requires-Dist: pypdf2
